{
  "market_regime": {
    "name": "Market Regime",
    "value": "Bull Quiet",
    "regime": "Bull Quiet",
    "confidence": "high",
    "interpretation": "Bull Quiet regime. Risk: Risk On | Rates: Rising Rates",
    "components": {
      "risk_sentiment": {
        "name": "Risk Sentiment",
        "value": "risk_on",
        "signal": "risk_on",
        "interpretation": "Strong risk-on: Equities rising, volatility low and falling",
        "components": {
          "spy_trend": "strong_uptrend",
          "spy_price": 747.4099731445312,
          "vix_level": "normal",
          "vix_value": 16.639999389648438,
          "vix_trend": "falling"
        },
        "timestamp": "2026-07-23T16:18:30.850950"
      },
      "dollar_strength": {
        "name": "Dollar Strength",
        "value": "neutral",
        "signal": "neutral",
        "interpretation": "Dollar stable: Neutral for commodities",
        "components": {
          "uup_price": 28.450000762939453,
          "trend": "strong_uptrend",
          "momentum": 0.0,
          "smas": {
            "sma20": 28.401999950408936,
            "sma50": 28.074800148010254,
            "sma200": 27.445076265335082
          }
        },
        "timestamp": "2026-07-23T16:18:30.853555"
      },
      "real_rates": {
        "name": "Real Rates",
        "value": "rising_rates",
        "signal": "rising_rates",
        "interpretation": "Rates rising: Headwind for growth stocks, favor value/financials",
        "components": {
          "tlt_price": 83.44000244140625,
          "trend": "downtrend",
          "momentum": -2.8443440254188768,
          "smas": {
            "sma20": 85.0357894897461,
            "sma50": 84.85088973999024,
            "sma200": 85.98506233215332
          }
        },
        "timestamp": "2026-07-23T16:18:30.856008"
      },
      "commodity_strength": {
        "name": "Commodity Strength",
        "value": "commodities_mixed",
        "signal": "commodities_mixed",
        "interpretation": "Mixed commodity signals: Sector-specific factors at play",
        "components": {
          "gld": {
            "name": "Gold",
            "price": 379.1199951171875,
            "trend": "neutral",
            "momentum": 0.47704541450994675,
            "signal": "positive"
          },
          "slv": {
            "name": "Silver",
            "price": 53.91999816894531,
            "trend": "neutral",
            "momentum": -3.2478043928912292,
            "signal": "negative"
          },
          "xle": {
            "name": "Energy",
            "price": 59.20000076293945,
            "trend": "strong_uptrend",
            "momentum": 8.703638924258161,
            "signal": "strong_positive"
          }
        },
        "timestamp": "2026-07-23T16:18:30.863113"
      }
    },
    "timestamp": "2026-07-23T16:18:30.863143"
  },
  "indicators": {
    "risk_sentiment": {
      "name": "Risk Sentiment",
      "value": "risk_on",
      "signal": "risk_on",
      "interpretation": "Strong risk-on: Equities rising, volatility low and falling",
      "components": {
        "spy_trend": "strong_uptrend",
        "spy_price": 747.4099731445312,
        "vix_level": "normal",
        "vix_value": 16.639999389648438,
        "vix_trend": "falling"
      },
      "timestamp": "2026-07-23T16:18:30.850950"
    },
    "dollar_strength": {
      "name": "Dollar Strength",
      "value": "neutral",
      "signal": "neutral",
      "interpretation": "Dollar stable: Neutral for commodities",
      "components": {
        "uup_price": 28.450000762939453,
        "trend": "strong_uptrend",
        "momentum": 0.0,
        "smas": {
          "sma20": 28.401999950408936,
          "sma50": 28.074800148010254,
          "sma200": 27.445076265335082
        }
      },
      "timestamp": "2026-07-23T16:18:30.853555"
    },
    "real_rates": {
      "name": "Real Rates",
      "value": "rising_rates",
      "signal": "rising_rates",
      "interpretation": "Rates rising: Headwind for growth stocks, favor value/financials",
      "components": {
        "tlt_price": 83.44000244140625,
        "trend": "downtrend",
        "momentum": -2.8443440254188768,
        "smas": {
          "sma20": 85.0357894897461,
          "sma50": 84.85088973999024,
          "sma200": 85.98506233215332
        }
      },
      "timestamp": "2026-07-23T16:18:30.856008"
    },
    "commodity_strength": {
      "name": "Commodity Strength",
      "value": "commodities_mixed",
      "signal": "commodities_mixed",
      "interpretation": "Mixed commodity signals: Sector-specific factors at play",
      "components": {
        "gld": {
          "name": "Gold",
          "price": 379.1199951171875,
          "trend": "neutral",
          "momentum": 0.47704541450994675,
          "signal": "positive"
        },
        "slv": {
          "name": "Silver",
          "price": 53.91999816894531,
          "trend": "neutral",
          "momentum": -3.2478043928912292,
          "signal": "negative"
        },
        "xle": {
          "name": "Energy",
          "price": 59.20000076293945,
          "trend": "strong_uptrend",
          "momentum": 8.703638924258161,
          "signal": "strong_positive"
        }
      },
      "timestamp": "2026-07-23T16:18:30.863113"
    }
  },
  "metadata": {
    "generated_at": "2026-07-23T16:18:30.863146",
    "data_source": "EOD historical data",
    "lookback_days": 250
  }
}