{
  "last_updated_utc": "2026-04-29T20:57:01.433810+00:00",
  "error": "",
  "results": [
    {
      "trade": {
        "ticker": "XLU",
        "action": "buy",
        "notional_value": 8000
      },
      "status": "skipped",
      "reason": "No available buying power."
    },
    {
      "trade": {
        "ticker": "XLE",
        "action": "buy",
        "notional_value": 8000
      },
      "status": "skipped",
      "reason": "No available buying power."
    },
    {
      "trade": {
        "ticker": "IAU",
        "action": "buy",
        "notional_value": 5000
      },
      "status": "skipped",
      "reason": "No available buying power."
    }
  ]
}