{
  "generated_at_utc": "2026-03-15T07:04:40.199268+00:00",
  "covered_calls": [
    {
      "ticker": "GLD",
      "strategy": "covered_call",
      "expiration": "2026-03-31",
      "dte": 16,
      "current_price": 460.84,
      "contracts": 2,
      "option_type": "call",
      "contract": {
        "contract_symbol": "GLD260331C00488000",
        "strike": 488.0,
        "last_price": 3.12,
        "bid": 2.91,
        "ask": 3.25,
        "mid_price": 3.08,
        "implied_volatility": 0.3029,
        "open_interest": 315,
        "volume": 4,
        "spread_pct": 0.1104,
        "moneyness_pct": 0.0589
      },
      "rationale": "Generate premium against an existing equity position using a moderately OTM call."
    },
    {
      "ticker": "GLD",
      "strategy": "covered_call",
      "expiration": "2026-04-02",
      "dte": 18,
      "current_price": 460.84,
      "contracts": 2,
      "option_type": "call",
      "contract": {
        "contract_symbol": "GLD260402C00486000",
        "strike": 486.0,
        "last_price": 4.6,
        "bid": 3.95,
        "ask": 4.4,
        "mid_price": 4.175,
        "implied_volatility": 0.3107,
        "open_interest": 128,
        "volume": 8,
        "spread_pct": 0.1078,
        "moneyness_pct": 0.0546
      },
      "rationale": "Generate premium against an existing equity position using a moderately OTM call."
    },
    {
      "ticker": "XLU",
      "strategy": "covered_call",
      "expiration": "2026-04-02",
      "dte": 18,
      "current_price": 46.96,
      "contracts": 21,
      "option_type": "call",
      "contract": {
        "contract_symbol": "XLU260402C00049500",
        "strike": 49.5,
        "last_price": 0.23,
        "bid": 0.0,
        "ask": 0.49,
        "mid_price": 0.23,
        "implied_volatility": 0.3213,
        "open_interest": 182,
        "volume": 29,
        "spread_pct": NaN,
        "moneyness_pct": 0.0541
      },
      "rationale": "Generate premium against an existing equity position using a moderately OTM call."
    }
  ],
  "cash_secured_puts": [
    {
      "ticker": "AAPL",
      "strategy": "cash_secured_put",
      "expiration": "2026-04-02",
      "dte": 18,
      "current_price": 250.12,
      "contracts": 1,
      "option_type": "put",
      "contract": {
        "contract_symbol": "AAPL260402P00235000",
        "strike": 235.0,
        "last_price": 2.6,
        "bid": 2.56,
        "ask": 2.67,
        "mid_price": 2.615,
        "implied_volatility": 0.3661,
        "open_interest": 747,
        "volume": 106,
        "spread_pct": 0.0421,
        "moneyness_pct": 0.0605
      },
      "rationale": "Get paid to enter a desired position below spot using a moderately OTM put."
    },
    {
      "ticker": "AAPL",
      "strategy": "cash_secured_put",
      "expiration": "2026-04-10",
      "dte": 26,
      "current_price": 250.12,
      "contracts": 1,
      "option_type": "put",
      "contract": {
        "contract_symbol": "AAPL260410P00235000",
        "strike": 235.0,
        "last_price": 3.25,
        "bid": 3.3,
        "ask": 3.5,
        "mid_price": 3.4,
        "implied_volatility": 0.3475,
        "open_interest": 243,
        "volume": 91,
        "spread_pct": 0.0588,
        "moneyness_pct": 0.0605
      },
      "rationale": "Get paid to enter a desired position below spot using a moderately OTM put."
    },
    {
      "ticker": "AMD",
      "strategy": "cash_secured_put",
      "expiration": "2026-04-02",
      "dte": 18,
      "current_price": 193.39,
      "contracts": 1,
      "option_type": "put",
      "contract": {
        "contract_symbol": "AMD260402P00180000",
        "strike": 180.0,
        "last_price": 5.07,
        "bid": 4.9,
        "ask": 5.05,
        "mid_price": 4.975,
        "implied_volatility": 0.6079,
        "open_interest": 1438,
        "volume": 404,
        "spread_pct": 0.0302,
        "moneyness_pct": 0.0692
      },
      "rationale": "Get paid to enter a desired position below spot using a moderately OTM put."
    },
    {
      "ticker": "AMD",
      "strategy": "cash_secured_put",
      "expiration": "2026-04-10",
      "dte": 26,
      "current_price": 193.39,
      "contracts": 1,
      "option_type": "put",
      "contract": {
        "contract_symbol": "AMD260410P00180000",
        "strike": 180.0,
        "last_price": 6.4,
        "bid": 6.15,
        "ask": 6.35,
        "mid_price": 6.25,
        "implied_volatility": 0.5809,
        "open_interest": 1209,
        "volume": 143,
        "spread_pct": 0.032,
        "moneyness_pct": 0.0692
      },
      "rationale": "Get paid to enter a desired position below spot using a moderately OTM put."
    },
    {
      "ticker": "AMZN",
      "strategy": "cash_secured_put",
      "expiration": "2026-04-02",
      "dte": 18,
      "current_price": 207.67,
      "contracts": 1,
      "option_type": "put",
      "contract": {
        "contract_symbol": "AMZN260402P00195000",
        "strike": 195.0,
        "last_price": 2.91,
        "bid": 2.81,
        "ask": 3.25,
        "mid_price": 3.03,
        "implied_volatility": 0.4395,
        "open_interest": 966,
        "volume": 154,
        "spread_pct": 0.1452,
        "moneyness_pct": 0.061
      },
      "rationale": "Get paid to enter a desired position below spot using a moderately OTM put."
    },
    {
      "ticker": "AMZN",
      "strategy": "cash_secured_put",
      "expiration": "2026-04-10",
      "dte": 26,
      "current_price": 207.67,
      "contracts": 1,
      "option_type": "put",
      "contract": {
        "contract_symbol": "AMZN260410P00195000",
        "strike": 195.0,
        "last_price": 3.65,
        "bid": 3.6,
        "ask": 3.75,
        "mid_price": 3.675,
        "implied_volatility": 0.3962,
        "open_interest": 1173,
        "volume": 236,
        "spread_pct": 0.0408,
        "moneyness_pct": 0.061
      },
      "rationale": "Get paid to enter a desired position below spot using a moderately OTM put."
    },
    {
      "ticker": "AVGO",
      "strategy": "cash_secured_put",
      "expiration": "2026-04-02",
      "dte": 18,
      "current_price": 322.16,
      "contracts": 1,
      "option_type": "put",
      "contract": {
        "contract_symbol": "AVGO260402P00305000",
        "strike": 305.0,
        "last_price": 8.56,
        "bid": 8.1,
        "ask": 8.75,
        "mid_price": 8.425,
        "implied_volatility": 0.5442,
        "open_interest": 131,
        "volume": 36,
        "spread_pct": 0.0772,
        "moneyness_pct": 0.0533
      },
      "rationale": "Get paid to enter a desired position below spot using a moderately OTM put."
    },
    {
      "ticker": "AVGO",
      "strategy": "cash_secured_put",
      "expiration": "2026-04-10",
      "dte": 26,
      "current_price": 322.16,
      "contracts": 1,
      "option_type": "put",
      "contract": {
        "contract_symbol": "AVGO260410P00305000",
        "strike": 305.0,
        "last_price": 10.58,
        "bid": 10.05,
        "ask": 10.95,
        "mid_price": 10.5,
        "implied_volatility": 0.5231,
        "open_interest": 115,
        "volume": 36,
        "spread_pct": 0.0857,
        "moneyness_pct": 0.0533
      },
      "rationale": "Get paid to enter a desired position below spot using a moderately OTM put."
    },
    {
      "ticker": "CEG",
      "strategy": "cash_secured_put",
      "expiration": "2026-04-02",
      "dte": 18,
      "current_price": 301.77,
      "contracts": 1,
      "option_type": "put",
      "contract": {
        "contract_symbol": "CEG260402P00300000",
        "strike": 300.0,
        "last_price": 15.49,
        "bid": 14.7,
        "ask": 17.0,
        "mid_price": 15.85,
        "implied_volatility": 0.611,
        "open_interest": 536,
        "volume": 2,
        "spread_pct": 0.1451,
        "moneyness_pct": 0.0059
      },
      "rationale": "Get paid to enter a desired position below spot using a moderately OTM put."
    },
    {
      "ticker": "CEG",
      "strategy": "cash_secured_put",
      "expiration": "2026-04-10",
      "dte": 26,
      "current_price": 301.77,
      "contracts": 1,
      "option_type": "put",
      "contract": {
        "contract_symbol": "CEG260410P00300000",
        "strike": 300.0,
        "last_price": 17.96,
        "bid": 16.7,
        "ask": 18.5,
        "mid_price": 17.6,
        "implied_volatility": 0.5664,
        "open_interest": 197,
        "volume": 2,
        "spread_pct": 0.1023,
        "moneyness_pct": 0.0059
      },
      "rationale": "Get paid to enter a desired position below spot using a moderately OTM put."
    },
    {
      "ticker": "GLD",
      "strategy": "cash_secured_put",
      "expiration": "2026-03-31",
      "dte": 16,
      "current_price": 460.84,
      "contracts": 1,
      "option_type": "put",
      "contract": {
        "contract_symbol": "GLD260331P00434000",
        "strike": 434.0,
        "last_price": 2.91,
        "bid": 3.05,
        "ask": 3.4,
        "mid_price": 3.225,
        "implied_volatility": 0.3245,
        "open_interest": 155,
        "volume": 2,
        "spread_pct": 0.1085,
        "moneyness_pct": 0.0582
      },
      "rationale": "Get paid to enter a desired position below spot using a moderately OTM put."
    },
    {
      "ticker": "GLD",
      "strategy": "cash_secured_put",
      "expiration": "2026-04-02",
      "dte": 18,
      "current_price": 460.84,
      "contracts": 1,
      "option_type": "put",
      "contract": {
        "contract_symbol": "GLD260402P00435000",
        "strike": 435.0,
        "last_price": 3.87,
        "bid": 3.7,
        "ask": 4.05,
        "mid_price": 3.875,
        "implied_volatility": 0.3218,
        "open_interest": 867,
        "volume": 48,
        "spread_pct": 0.0903,
        "moneyness_pct": 0.0561
      },
      "rationale": "Get paid to enter a desired position below spot using a moderately OTM put."
    }
  ],
  "protective_puts": [
    {
      "ticker": "GLD",
      "strategy": "protective_put",
      "expiration": "2026-03-31",
      "dte": 16,
      "current_price": 460.84,
      "contracts": 2,
      "option_type": "put",
      "contract": {
        "contract_symbol": "GLD260331P00434000",
        "strike": 434.0,
        "last_price": 2.91,
        "bid": 3.05,
        "ask": 3.4,
        "mid_price": 3.225,
        "implied_volatility": 0.3245,
        "open_interest": 155,
        "volume": 2,
        "spread_pct": 0.1085,
        "moneyness_pct": 0.0582
      },
      "rationale": "Add downside protection to an existing equity holding with a moderately OTM put."
    },
    {
      "ticker": "GLD",
      "strategy": "protective_put",
      "expiration": "2026-04-02",
      "dte": 18,
      "current_price": 460.84,
      "contracts": 2,
      "option_type": "put",
      "contract": {
        "contract_symbol": "GLD260402P00435000",
        "strike": 435.0,
        "last_price": 3.87,
        "bid": 3.7,
        "ask": 4.05,
        "mid_price": 3.875,
        "implied_volatility": 0.3218,
        "open_interest": 867,
        "volume": 48,
        "spread_pct": 0.0903,
        "moneyness_pct": 0.0561
      },
      "rationale": "Add downside protection to an existing equity holding with a moderately OTM put."
    },
    {
      "ticker": "XLU",
      "strategy": "protective_put",
      "expiration": "2026-04-02",
      "dte": 18,
      "current_price": 46.96,
      "contracts": 21,
      "option_type": "put",
      "contract": {
        "contract_symbol": "XLU260402P00044500",
        "strike": 44.5,
        "last_price": 0.29,
        "bid": 0.0,
        "ask": 1.4,
        "mid_price": 0.29,
        "implied_volatility": 0.5855,
        "open_interest": 173,
        "volume": 2,
        "spread_pct": NaN,
        "moneyness_pct": 0.0524
      },
      "rationale": "Add downside protection to an existing equity holding with a moderately OTM put."
    }
  ],
  "long_option_ideas": [
    {
      "ticker": "GLD",
      "strategy": "long_call",
      "expiration": "2026-03-31",
      "dte": 16,
      "current_price": 460.84,
      "contracts": 1,
      "option_type": "call",
      "contract": {
        "contract_symbol": "GLD260331C00475000",
        "strike": 475.0,
        "last_price": 6.4,
        "bid": 5.9,
        "ask": 6.3,
        "mid_price": 6.1,
        "implied_volatility": 0.3,
        "open_interest": 3932,
        "volume": 183,
        "spread_pct": 0.0656,
        "moneyness_pct": 0.0307
      },
      "rationale": "Directional upside expression on a liquid ETF/underlying using a slightly OTM call."
    },
    {
      "ticker": "GLD",
      "strategy": "long_put",
      "expiration": "2026-03-31",
      "dte": 16,
      "current_price": 460.84,
      "contracts": 1,
      "option_type": "put",
      "contract": {
        "contract_symbol": "GLD260331P00447000",
        "strike": 447.0,
        "last_price": 5.23,
        "bid": 5.75,
        "ask": 6.2,
        "mid_price": 5.975,
        "implied_volatility": 0.3035,
        "open_interest": 195,
        "volume": 5,
        "spread_pct": 0.0753,
        "moneyness_pct": 0.03
      },
      "rationale": "Directional downside hedge or bearish expression on a liquid ETF/underlying using a slightly OTM put."
    },
    {
      "ticker": "GLD",
      "strategy": "long_call",
      "expiration": "2026-04-02",
      "dte": 18,
      "current_price": 460.84,
      "contracts": 1,
      "option_type": "call",
      "contract": {
        "contract_symbol": "GLD260402C00475000",
        "strike": 475.0,
        "last_price": 7.0,
        "bid": 6.85,
        "ask": 7.3,
        "mid_price": 7.075,
        "implied_volatility": 0.3097,
        "open_interest": 606,
        "volume": 28,
        "spread_pct": 0.0636,
        "moneyness_pct": 0.0307
      },
      "rationale": "Directional upside expression on a liquid ETF/underlying using a slightly OTM call."
    },
    {
      "ticker": "GLD",
      "strategy": "long_put",
      "expiration": "2026-04-02",
      "dte": 18,
      "current_price": 460.84,
      "contracts": 1,
      "option_type": "put",
      "contract": {
        "contract_symbol": "GLD260402P00448000",
        "strike": 448.0,
        "last_price": 5.9,
        "bid": 6.75,
        "ask": 7.2,
        "mid_price": 6.975,
        "implied_volatility": 0.3045,
        "open_interest": 124,
        "volume": 4,
        "spread_pct": 0.0645,
        "moneyness_pct": 0.0279
      },
      "rationale": "Directional downside hedge or bearish expression on a liquid ETF/underlying using a slightly OTM put."
    },
    {
      "ticker": "QQQ",
      "strategy": "long_call",
      "expiration": "2026-03-31",
      "dte": 16,
      "current_price": 593.72,
      "contracts": 1,
      "option_type": "call",
      "contract": {
        "contract_symbol": "QQQ260331C00612000",
        "strike": 612.0,
        "last_price": 5.15,
        "bid": 4.89,
        "ask": 4.99,
        "mid_price": 4.94,
        "implied_volatility": 0.2308,
        "open_interest": 431,
        "volume": 142,
        "spread_pct": 0.0202,
        "moneyness_pct": 0.0308
      },
      "rationale": "Directional upside expression on a liquid ETF/underlying using a slightly OTM call."
    },
    {
      "ticker": "QQQ",
      "strategy": "long_put",
      "expiration": "2026-03-31",
      "dte": 16,
      "current_price": 593.72,
      "contracts": 1,
      "option_type": "put",
      "contract": {
        "contract_symbol": "QQQ260331P00576000",
        "strike": 576.0,
        "last_price": 8.32,
        "bid": 8.67,
        "ask": 8.78,
        "mid_price": 8.725,
        "implied_volatility": 0.3201,
        "open_interest": 215,
        "volume": 93,
        "spread_pct": 0.0126,
        "moneyness_pct": 0.0298
      },
      "rationale": "Directional downside hedge or bearish expression on a liquid ETF/underlying using a slightly OTM put."
    },
    {
      "ticker": "QQQ",
      "strategy": "long_call",
      "expiration": "2026-04-02",
      "dte": 18,
      "current_price": 593.72,
      "contracts": 1,
      "option_type": "call",
      "contract": {
        "contract_symbol": "QQQ260402C00612000",
        "strike": 612.0,
        "last_price": 5.9,
        "bid": 5.72,
        "ask": 5.81,
        "mid_price": 5.765,
        "implied_volatility": 0.236,
        "open_interest": 364,
        "volume": 177,
        "spread_pct": 0.0156,
        "moneyness_pct": 0.0308
      },
      "rationale": "Directional upside expression on a liquid ETF/underlying using a slightly OTM call."
    },
    {
      "ticker": "QQQ",
      "strategy": "long_put",
      "expiration": "2026-04-02",
      "dte": 18,
      "current_price": 593.72,
      "contracts": 1,
      "option_type": "put",
      "contract": {
        "contract_symbol": "QQQ260402P00575000",
        "strike": 575.0,
        "last_price": 9.27,
        "bid": 9.21,
        "ask": 9.32,
        "mid_price": 9.265,
        "implied_volatility": 0.3211,
        "open_interest": 1331,
        "volume": 217,
        "spread_pct": 0.0119,
        "moneyness_pct": 0.0315
      },
      "rationale": "Directional downside hedge or bearish expression on a liquid ETF/underlying using a slightly OTM put."
    },
    {
      "ticker": "SPY",
      "strategy": "long_call",
      "expiration": "2026-03-31",
      "dte": 16,
      "current_price": 662.29,
      "contracts": 1,
      "option_type": "call",
      "contract": {
        "contract_symbol": "SPY260331C00682000",
        "strike": 682.0,
        "last_price": 4.0,
        "bid": 4.01,
        "ask": 4.06,
        "mid_price": 4.035,
        "implied_volatility": 0.195,
        "open_interest": 2073,
        "volume": 355,
        "spread_pct": 0.0124,
        "moneyness_pct": 0.0298
      },
      "rationale": "Directional upside expression on a liquid ETF/underlying using a slightly OTM call."
    },
    {
      "ticker": "SPY",
      "strategy": "long_put",
      "expiration": "2026-03-31",
      "dte": 16,
      "current_price": 662.29,
      "contracts": 1,
      "option_type": "put",
      "contract": {
        "contract_symbol": "SPY260331P00642000",
        "strike": 642.0,
        "last_price": 7.94,
        "bid": 8.06,
        "ask": 8.11,
        "mid_price": 8.085,
        "implied_volatility": 0.2901,
        "open_interest": 742,
        "volume": 81,
        "spread_pct": 0.0062,
        "moneyness_pct": 0.0306
      },
      "rationale": "Directional downside hedge or bearish expression on a liquid ETF/underlying using a slightly OTM put."
    },
    {
      "ticker": "SPY",
      "strategy": "long_call",
      "expiration": "2026-04-02",
      "dte": 18,
      "current_price": 662.29,
      "contracts": 1,
      "option_type": "call",
      "contract": {
        "contract_symbol": "SPY260402C00682000",
        "strike": 682.0,
        "last_price": 4.74,
        "bid": 4.75,
        "ask": 4.8,
        "mid_price": 4.775,
        "implied_volatility": 0.1995,
        "open_interest": 668,
        "volume": 165,
        "spread_pct": 0.0105,
        "moneyness_pct": 0.0298
      },
      "rationale": "Directional upside expression on a liquid ETF/underlying using a slightly OTM call."
    },
    {
      "ticker": "SPY",
      "strategy": "long_put",
      "expiration": "2026-04-02",
      "dte": 18,
      "current_price": 662.29,
      "contracts": 1,
      "option_type": "put",
      "contract": {
        "contract_symbol": "SPY260402P00640000",
        "strike": 640.0,
        "last_price": 8.28,
        "bid": 8.3,
        "ask": 8.36,
        "mid_price": 8.33,
        "implied_volatility": 0.2914,
        "open_interest": 1734,
        "volume": 588,
        "spread_pct": 0.0072,
        "moneyness_pct": 0.0337
      },
      "rationale": "Directional downside hedge or bearish expression on a liquid ETF/underlying using a slightly OTM put."
    }
  ],
  "errors": []
}