{
  "generated_at_utc": "2026-04-20T20:48:40.673301+00:00",
  "covered_calls": [],
  "cash_secured_puts": [
    {
      "ticker": "AAPL",
      "strategy": "cash_secured_put",
      "expiration": "2026-05-08",
      "dte": 18,
      "current_price": 273.05,
      "contracts": 1,
      "option_type": "put",
      "contract": {
        "contract_symbol": "AAPL260508P00255000",
        "strike": 255.0,
        "last_price": 2.0,
        "bid": 1.83,
        "ask": 2.07,
        "mid_price": 1.95,
        "implied_volatility": 0.3367,
        "open_interest": 419,
        "volume": 317,
        "spread_pct": 0.1231,
        "moneyness_pct": 0.0661
      },
      "rationale": "Get paid to enter a desired position below spot using a moderately OTM put."
    },
    {
      "ticker": "AAPL",
      "strategy": "cash_secured_put",
      "expiration": "2026-05-15",
      "dte": 25,
      "current_price": 273.05,
      "contracts": 1,
      "option_type": "put",
      "contract": {
        "contract_symbol": "AAPL260515P00255000",
        "strike": 255.0,
        "last_price": 2.57,
        "bid": 2.4,
        "ask": 2.59,
        "mid_price": 2.495,
        "implied_volatility": 0.3144,
        "open_interest": 7345,
        "volume": 1007,
        "spread_pct": 0.0762,
        "moneyness_pct": 0.0661
      },
      "rationale": "Get paid to enter a desired position below spot using a moderately OTM put."
    },
    {
      "ticker": "AMD",
      "strategy": "cash_secured_put",
      "expiration": "2026-05-08",
      "dte": 18,
      "current_price": 274.95,
      "contracts": 1,
      "option_type": "put",
      "contract": {
        "contract_symbol": "AMD260508P00260000",
        "strike": 260.0,
        "last_price": 8.8,
        "bid": 8.6,
        "ask": 8.95,
        "mid_price": 8.775,
        "implied_volatility": 0.6204,
        "open_interest": 420,
        "volume": 233,
        "spread_pct": 0.0399,
        "moneyness_pct": 0.0544
      },
      "rationale": "Get paid to enter a desired position below spot using a moderately OTM put."
    },
    {
      "ticker": "AMD",
      "strategy": "cash_secured_put",
      "expiration": "2026-05-15",
      "dte": 25,
      "current_price": 274.95,
      "contracts": 1,
      "option_type": "put",
      "contract": {
        "contract_symbol": "AMD260515P00260000",
        "strike": 260.0,
        "last_price": 10.55,
        "bid": 10.3,
        "ask": 10.65,
        "mid_price": 10.475,
        "implied_volatility": 0.5945,
        "open_interest": 2068,
        "volume": 1489,
        "spread_pct": 0.0334,
        "moneyness_pct": 0.0544
      },
      "rationale": "Get paid to enter a desired position below spot using a moderately OTM put."
    },
    {
      "ticker": "AMZN",
      "strategy": "cash_secured_put",
      "expiration": "2026-05-08",
      "dte": 18,
      "current_price": 248.28,
      "contracts": 1,
      "option_type": "put",
      "contract": {
        "contract_symbol": "AMZN260508P00235000",
        "strike": 235.0,
        "last_price": 4.8,
        "bid": 4.65,
        "ask": 4.85,
        "mid_price": 4.75,
        "implied_volatility": 0.4612,
        "open_interest": 456,
        "volume": 542,
        "spread_pct": 0.0421,
        "moneyness_pct": 0.0535
      },
      "rationale": "Get paid to enter a desired position below spot using a moderately OTM put."
    },
    {
      "ticker": "AMZN",
      "strategy": "cash_secured_put",
      "expiration": "2026-05-15",
      "dte": 25,
      "current_price": 248.28,
      "contracts": 1,
      "option_type": "put",
      "contract": {
        "contract_symbol": "AMZN260515P00235000",
        "strike": 235.0,
        "last_price": 5.45,
        "bid": 5.2,
        "ask": 5.35,
        "mid_price": 5.275,
        "implied_volatility": 0.4164,
        "open_interest": 8836,
        "volume": 382,
        "spread_pct": 0.0284,
        "moneyness_pct": 0.0535
      },
      "rationale": "Get paid to enter a desired position below spot using a moderately OTM put."
    },
    {
      "ticker": "AVGO",
      "strategy": "cash_secured_put",
      "expiration": "2026-05-08",
      "dte": 18,
      "current_price": 399.63,
      "contracts": 1,
      "option_type": "put",
      "contract": {
        "contract_symbol": "AVGO260508P00375000",
        "strike": 375.0,
        "last_price": 6.88,
        "bid": 5.85,
        "ask": 6.75,
        "mid_price": 6.3,
        "implied_volatility": 0.459,
        "open_interest": 754,
        "volume": 36,
        "spread_pct": 0.1429,
        "moneyness_pct": 0.0616
      },
      "rationale": "Get paid to enter a desired position below spot using a moderately OTM put."
    },
    {
      "ticker": "AVGO",
      "strategy": "cash_secured_put",
      "expiration": "2026-05-15",
      "dte": 25,
      "current_price": 399.63,
      "contracts": 1,
      "option_type": "put",
      "contract": {
        "contract_symbol": "AVGO260515P00380000",
        "strike": 380.0,
        "last_price": 9.48,
        "bid": 8.75,
        "ask": 9.85,
        "mid_price": 9.3,
        "implied_volatility": 0.4337,
        "open_interest": 2186,
        "volume": 1655,
        "spread_pct": 0.1183,
        "moneyness_pct": 0.0491
      },
      "rationale": "Get paid to enter a desired position below spot using a moderately OTM put."
    },
    {
      "ticker": "CEG",
      "strategy": "cash_secured_put",
      "expiration": "2026-05-15",
      "dte": 25,
      "current_price": 287.56,
      "contracts": 1,
      "option_type": "put",
      "contract": {
        "contract_symbol": "CEG260515P00270000",
        "strike": 270.0,
        "last_price": 7.6,
        "bid": 8.0,
        "ask": 9.2,
        "mid_price": 8.6,
        "implied_volatility": 0.5349,
        "open_interest": 769,
        "volume": 10,
        "spread_pct": 0.1395,
        "moneyness_pct": 0.0611
      },
      "rationale": "Get paid to enter a desired position below spot using a moderately OTM put."
    },
    {
      "ticker": "CRWD",
      "strategy": "cash_secured_put",
      "expiration": "2026-05-08",
      "dte": 18,
      "current_price": 433.15,
      "contracts": 1,
      "option_type": "put",
      "contract": {
        "contract_symbol": "CRWD260508P00400000",
        "strike": 400.0,
        "last_price": 7.35,
        "bid": 7.0,
        "ask": 7.65,
        "mid_price": 7.325,
        "implied_volatility": 0.5175,
        "open_interest": 275,
        "volume": 41,
        "spread_pct": 0.0887,
        "moneyness_pct": 0.0765
      },
      "rationale": "Get paid to enter a desired position below spot using a moderately OTM put."
    },
    {
      "ticker": "CRWD",
      "strategy": "cash_secured_put",
      "expiration": "2026-05-15",
      "dte": 25,
      "current_price": 433.15,
      "contracts": 1,
      "option_type": "put",
      "contract": {
        "contract_symbol": "CRWD260515P00410000",
        "strike": 410.0,
        "last_price": 11.58,
        "bid": 11.25,
        "ask": 11.95,
        "mid_price": 11.6,
        "implied_volatility": 0.4812,
        "open_interest": 714,
        "volume": 16,
        "spread_pct": 0.0603,
        "moneyness_pct": 0.0534
      },
      "rationale": "Get paid to enter a desired position below spot using a moderately OTM put."
    },
    {
      "ticker": "DIA",
      "strategy": "cash_secured_put",
      "expiration": "2026-05-08",
      "dte": 18,
      "current_price": 494.33,
      "contracts": 1,
      "option_type": "put",
      "contract": {
        "contract_symbol": "DIA260508P00477000",
        "strike": 477.0,
        "last_price": 2.34,
        "bid": 2.13,
        "ask": 2.43,
        "mid_price": 2.28,
        "implied_volatility": 0.1901,
        "open_interest": 721,
        "volume": 3,
        "spread_pct": 0.1316,
        "moneyness_pct": 0.0351
      },
      "rationale": "Get paid to enter a desired position below spot using a moderately OTM put."
    }
  ],
  "protective_puts": [],
  "long_option_ideas": [
    {
      "ticker": "GLD",
      "strategy": "long_call",
      "expiration": "2026-05-08",
      "dte": 18,
      "current_price": 442.09,
      "contracts": 1,
      "option_type": "call",
      "contract": {
        "contract_symbol": "GLD260508C00455000",
        "strike": 455.0,
        "last_price": 5.23,
        "bid": 5.1,
        "ask": 5.45,
        "mid_price": 5.275,
        "implied_volatility": 0.2618,
        "open_interest": 186,
        "volume": 179,
        "spread_pct": 0.0664,
        "moneyness_pct": 0.0292
      },
      "rationale": "Directional upside expression on a liquid ETF/underlying using a slightly OTM call."
    },
    {
      "ticker": "GLD",
      "strategy": "long_put",
      "expiration": "2026-05-08",
      "dte": 18,
      "current_price": 442.09,
      "contracts": 1,
      "option_type": "put",
      "contract": {
        "contract_symbol": "GLD260508P00430000",
        "strike": 430.0,
        "last_price": 5.17,
        "bid": 4.95,
        "ask": 5.3,
        "mid_price": 5.125,
        "implied_volatility": 0.2578,
        "open_interest": 245,
        "volume": 306,
        "spread_pct": 0.0683,
        "moneyness_pct": 0.0273
      },
      "rationale": "Directional downside hedge or bearish expression on a liquid ETF/underlying using a slightly OTM put."
    },
    {
      "ticker": "GLD",
      "strategy": "long_call",
      "expiration": "2026-05-15",
      "dte": 25,
      "current_price": 442.09,
      "contracts": 1,
      "option_type": "call",
      "contract": {
        "contract_symbol": "GLD260515C00455000",
        "strike": 455.0,
        "last_price": 7.2,
        "bid": 6.8,
        "ask": 7.3,
        "mid_price": 7.05,
        "implied_volatility": 0.2665,
        "open_interest": 8930,
        "volume": 90,
        "spread_pct": 0.0709,
        "moneyness_pct": 0.0292
      },
      "rationale": "Directional upside expression on a liquid ETF/underlying using a slightly OTM call."
    },
    {
      "ticker": "GLD",
      "strategy": "long_put",
      "expiration": "2026-05-15",
      "dte": 25,
      "current_price": 442.09,
      "contracts": 1,
      "option_type": "put",
      "contract": {
        "contract_symbol": "GLD260515P00430000",
        "strike": 430.0,
        "last_price": 6.52,
        "bid": 6.3,
        "ask": 6.65,
        "mid_price": 6.475,
        "implied_volatility": 0.2524,
        "open_interest": 6943,
        "volume": 3629,
        "spread_pct": 0.0541,
        "moneyness_pct": 0.0273
      },
      "rationale": "Directional downside hedge or bearish expression on a liquid ETF/underlying using a slightly OTM put."
    },
    {
      "ticker": "QQQ",
      "strategy": "long_call",
      "expiration": "2026-05-08",
      "dte": 18,
      "current_price": 646.79,
      "contracts": 1,
      "option_type": "call",
      "contract": {
        "contract_symbol": "QQQ260508C00665000",
        "strike": 665.0,
        "last_price": 4.41,
        "bid": 4.4,
        "ask": 4.46,
        "mid_price": 4.43,
        "implied_volatility": 0.1894,
        "open_interest": 20589,
        "volume": 921,
        "spread_pct": 0.0135,
        "moneyness_pct": 0.0282
      },
      "rationale": "Directional upside expression on a liquid ETF/underlying using a slightly OTM call."
    },
    {
      "ticker": "QQQ",
      "strategy": "long_put",
      "expiration": "2026-05-08",
      "dte": 18,
      "current_price": 646.79,
      "contracts": 1,
      "option_type": "put",
      "contract": {
        "contract_symbol": "QQQ260508P00627000",
        "strike": 627.0,
        "last_price": 5.49,
        "bid": 5.27,
        "ask": 5.31,
        "mid_price": 5.29,
        "implied_volatility": 0.2218,
        "open_interest": 194,
        "volume": 57,
        "spread_pct": 0.0076,
        "moneyness_pct": 0.0306
      },
      "rationale": "Directional downside hedge or bearish expression on a liquid ETF/underlying using a slightly OTM put."
    },
    {
      "ticker": "QQQ",
      "strategy": "long_call",
      "expiration": "2026-05-15",
      "dte": 25,
      "current_price": 646.79,
      "contracts": 1,
      "option_type": "call",
      "contract": {
        "contract_symbol": "QQQ260515C00665000",
        "strike": 665.0,
        "last_price": 6.18,
        "bid": 6.12,
        "ask": 6.18,
        "mid_price": 6.15,
        "implied_volatility": 0.1913,
        "open_interest": 31303,
        "volume": 1888,
        "spread_pct": 0.0098,
        "moneyness_pct": 0.0282
      },
      "rationale": "Directional upside expression on a liquid ETF/underlying using a slightly OTM call."
    },
    {
      "ticker": "QQQ",
      "strategy": "long_put",
      "expiration": "2026-05-15",
      "dte": 25,
      "current_price": 646.79,
      "contracts": 1,
      "option_type": "put",
      "contract": {
        "contract_symbol": "QQQ260515P00627000",
        "strike": 627.0,
        "last_price": 6.83,
        "bid": 6.79,
        "ask": 6.85,
        "mid_price": 6.82,
        "implied_volatility": 0.2164,
        "open_interest": 1888,
        "volume": 193,
        "spread_pct": 0.0088,
        "moneyness_pct": 0.0306
      },
      "rationale": "Directional downside hedge or bearish expression on a liquid ETF/underlying using a slightly OTM put."
    },
    {
      "ticker": "SPY",
      "strategy": "long_call",
      "expiration": "2026-05-08",
      "dte": 18,
      "current_price": 708.72,
      "contracts": 1,
      "option_type": "call",
      "contract": {
        "contract_symbol": "SPY260508C00730000",
        "strike": 730.0,
        "last_price": 2.04,
        "bid": 2.01,
        "ask": 2.03,
        "mid_price": 2.02,
        "implied_volatility": 0.136,
        "open_interest": 4705,
        "volume": 591,
        "spread_pct": 0.0099,
        "moneyness_pct": 0.03
      },
      "rationale": "Directional upside expression on a liquid ETF/underlying using a slightly OTM call."
    },
    {
      "ticker": "SPY",
      "strategy": "long_put",
      "expiration": "2026-05-08",
      "dte": 18,
      "current_price": 708.72,
      "contracts": 1,
      "option_type": "put",
      "contract": {
        "contract_symbol": "SPY260508P00687000",
        "strike": 687.0,
        "last_price": 3.59,
        "bid": 3.57,
        "ask": 3.59,
        "mid_price": 3.58,
        "implied_volatility": 0.1776,
        "open_interest": 5108,
        "volume": 156,
        "spread_pct": 0.0056,
        "moneyness_pct": 0.0306
      },
      "rationale": "Directional downside hedge or bearish expression on a liquid ETF/underlying using a slightly OTM put."
    },
    {
      "ticker": "SPY",
      "strategy": "long_call",
      "expiration": "2026-05-15",
      "dte": 25,
      "current_price": 708.72,
      "contracts": 1,
      "option_type": "call",
      "contract": {
        "contract_symbol": "SPY260515C00730000",
        "strike": 730.0,
        "last_price": 3.22,
        "bid": 3.2,
        "ask": 3.22,
        "mid_price": 3.21,
        "implied_volatility": 0.139,
        "open_interest": 13864,
        "volume": 3014,
        "spread_pct": 0.0062,
        "moneyness_pct": 0.03
      },
      "rationale": "Directional upside expression on a liquid ETF/underlying using a slightly OTM call."
    },
    {
      "ticker": "SPY",
      "strategy": "long_put",
      "expiration": "2026-05-15",
      "dte": 25,
      "current_price": 708.72,
      "contracts": 1,
      "option_type": "put",
      "contract": {
        "contract_symbol": "SPY260515P00687000",
        "strike": 687.0,
        "last_price": 4.92,
        "bid": 4.89,
        "ask": 4.93,
        "mid_price": 4.91,
        "implied_volatility": 0.1751,
        "open_interest": 2280,
        "volume": 302,
        "spread_pct": 0.0081,
        "moneyness_pct": 0.0306
      },
      "rationale": "Directional downside hedge or bearish expression on a liquid ETF/underlying using a slightly OTM put."
    }
  ],
  "errors": []
}